hidlroute/__init__.py
hidlroute/__version__.py
hidlroute/apps.py
hidlroute/asgi.py
hidlroute/cli.py
hidlroute/sites.py
hidlroute/urls.py
hidlroute/wsgi.py
hidlroute/auth/__init__.py
hidlroute/auth/admin.py
hidlroute/auth/apps.py
hidlroute/auth/models.py
hidlroute/auth/migrations/0001_initial.py
hidlroute/auth/migrations/__init__.py
hidlroute/contrib/__init__.py
hidlroute/contrib/dummy/__init__.py
hidlroute/contrib/dummy/admin.py
hidlroute/contrib/dummy/apps.py
hidlroute/contrib/dummy/factory.py
hidlroute/contrib/dummy/models.py
hidlroute/contrib/dummy/views.py
hidlroute/contrib/dummy/migrations/0001_initial.py
hidlroute/contrib/dummy/migrations/__init__.py
hidlroute/contrib/dummy/service/__init__.py
hidlroute/contrib/dummy/service/network.py
hidlroute/contrib/dummy/service/vpn.py
hidlroute/contrib/openvpn/__init__.py
hidlroute/contrib/openvpn/admin.py
hidlroute/contrib/openvpn/apps.py
hidlroute/contrib/openvpn/models.py
hidlroute/contrib/openvpn/migrations/0001_initial.py
hidlroute/contrib/openvpn/migrations/__init__.py
hidlroute/contrib/wireguard/__init__.py
hidlroute/contrib/wireguard/admin.py
hidlroute/contrib/wireguard/apps.py
hidlroute/contrib/wireguard/data.py
hidlroute/contrib/wireguard/factory.py
hidlroute/contrib/wireguard/models.py
hidlroute/contrib/wireguard/tests.py
hidlroute/contrib/wireguard/views.py
hidlroute/contrib/wireguard/migrations/0001_initial.py
hidlroute/contrib/wireguard/migrations/__init__.py
hidlroute/contrib/wireguard/service/__init__.py
hidlroute/contrib/wireguard/service/key.py
hidlroute/contrib/wireguard/service/peer.py
hidlroute/contrib/wireguard/service/wireguard_vpn.py
hidlroute/core/__init__.py
hidlroute/core/admin.py
hidlroute/core/admin_commons.py
hidlroute/core/apps.py
hidlroute/core/base_models.py
hidlroute/core/context_processors.py
hidlroute/core/errors.py
hidlroute/core/factory.py
hidlroute/core/forms.py
hidlroute/core/midleware.py
hidlroute/core/models.py
hidlroute/core/signals.py
hidlroute/core/types.py
hidlroute_server-0.0.11.dist-info/METADATA
hidlroute_server-0.0.11.dist-info/WHEEL
hidlroute_server-0.0.11.dist-info/entry_points.txt
hidlroute_server-0.0.11.dist-info/top_level.txt
hidlroute_server-0.0.11.dist-info/RECORD
