Metadata-Version: 2.1
Name: hidlroute-server
Version: 0.0.11
Summary: HidlRoute - advanced vpn management system
Home-page: https://github.com/jointbox/jointbox-cli
Author: HidlRoute
License: GPL-3.0-or-later
Keywords: vpn management server wireguard firewall routing
Platform: UNKNOWN
Classifier: Development Status :: 3 - Alpha
Classifier: Intended Audience :: Developers
Classifier: Topic :: Software Development :: Libraries :: Python Modules
Classifier: Topic :: Home Automation
Classifier: License :: OSI Approved :: GNU General Public License v3 or later (GPLv3+)
Classifier: Programming Language :: Python :: 3.8
Classifier: Programming Language :: Python :: 3.9
Classifier: Programming Language :: Python :: 3.10
Requires-Python: >3.8
Requires-Dist: cli-rack (==1.0.4)
Requires-Dist: PyYAML (==6.0)
Requires-Dist: django (==4.0.4)
Requires-Dist: django-environ (==0.8.1)
Requires-Dist: pydantic (==1.9.0)
Requires-Dist: psycopg2-binary (==2.9.3)
Requires-Dist: whitenoise (==6.1.0)
Requires-Dist: requests (==2.27.1)
Requires-Dist: gunicorn (==20.1.0)
Requires-Dist: celery[redis] (==5.2.6)
Requires-Dist: social-auth-app-django (==5.0.0)
Requires-Dist: django-jazzmin (==2.5.0)
Requires-Dist: django-two-factor-auth[phonenumbers] (==1.13.2)
Requires-Dist: django-defender (==0.9.4)
Requires-Dist: django-crispy-forms (==1.14.0)
Requires-Dist: django-polymorphic (==3.1.0)
Requires-Dist: django-treebeard (==4.5.1)
Requires-Dist: django-autoslug (==1.9.8)
Requires-Dist: django-admin-sortable2 (==2.0.4)
Requires-Dist: django-reverse-admin (==2.9.6)
Requires-Dist: django-netfields (==1.3.0)
Requires-Dist: pyroute2 (==0.6.9)
Requires-Dist: qrcode[pil] (==7.3.1)
Requires-Dist: python-iptables (==1.0.0)
Requires-Dist: PyNaCl (==1.5.0)
